AUTHORS.rst
CONTRIBUTING.rst
HISTORY.rst
LICENSE
MANIFEST.in
README.rst
setup.cfg
setup.py
docs/Makefile
docs/authors.rst
docs/conf.py
docs/contributing.rst
docs/history.rst
docs/index.rst
docs/installation.rst
docs/make.bat
docs/readme.rst
docs/usage.rst
pandoc_minted/__init__.py
pandoc_minted/cli.py
pandoc_minted.egg-info/PKG-INFO
pandoc_minted.egg-info/SOURCES.txt
pandoc_minted.egg-info/dependency_links.txt
pandoc_minted.egg-info/entry_points.txt
pandoc_minted.egg-info/not-zip-safe
pandoc_minted.egg-info/requires.txt
pandoc_minted.egg-info/top_level.txt
tests/__init__.py
tests/test_pandoc_minted.py