Metadata-Version: 1.1
Name: pandoc-minted
Version: 0.2.0
Summary: Pandoc filter to provide minted support (github.com/nick-ulle/pandoc-minted)
Home-page: https://github.com/D3f0/pandoc_minted
Author: Nahuel Defossé
Author-email: nahuel.defosse@gmail.com
License: MIT license
Keywords: pandoc_minted
Platform: UNKNOWN
Classifier: Development Status :: 2 - Pre-Alpha
Classifier: Intended Audience :: Developers
Classifier: License :: OSI Approved :: MIT License
Classifier: Natural Language :: English
Classifier: Programming Language :: Python :: 2
Classifier: Programming Language :: Python :: 2.6
Classifier: Programming Language :: Python :: 2.7
Classifier: Programming Language :: Python :: 3
Classifier: Programming Language :: Python :: 3.3
Classifier: Programming Language :: Python :: 3.4
Classifier: Programming Language :: Python :: 3.5
